pycostanza/__init__.py
pycostanza/cli.py
pycostanza/labels.py
pycostanza/misc.py
pycostanza/steepest.py
pycostanza-0.3.1.dist-info/DESCRIPTION.rst
pycostanza-0.3.1.dist-info/METADATA
pycostanza-0.3.1.dist-info/RECORD
pycostanza-0.3.1.dist-info/WHEEL
pycostanza-0.3.1.dist-info/entry_points.txt
pycostanza-0.3.1.dist-info/metadata.json
pycostanza-0.3.1.dist-info/top_level.txt
