Metadata-Version: 2.0
Name: pycostanza
Version: 0.3.1
Summary: Python version of Costanza
Home-page: https://gitlab.com/slcu/teamHJ/henrik_aahl/pycostanza
Author: Henrik Ahl
Author-email: hpa22@cam.ac.uk
License: GNU General Public License v3
Keywords: pycostanza
Platform: UNKNOWN
Classifier: Development Status :: 4 - Beta
Classifier: Intended Audience :: Developers
Classifier: Intended Audience :: Science/Research
Classifier: License :: OSI Approved :: GNU General Public License v3 (GPLv3)
Classifier: Natural Language :: English
Classifier: Programming Language :: Python :: 3
Classifier: Programming Language :: Python :: 3.4
Classifier: Programming Language :: Python :: 3.5
Classifier: Programming Language :: Python :: 3.6
Classifier: Programming Language :: Python :: 3.7
Requires-Dist: numpy (>=1.15.0)
Requires-Dist: scipy (>=1.0.0)
Requires-Dist: scikit-image (>=0.15)
Requires-Dist: mahotas (>=1.4.5)
Requires-Dist: networkx (>=2.0)
Requires-Dist: tifffile (>=2019.7.26)
